onnxsim_lm/__init__.py
onnxsim_lm/compress_model.py
onnxsim_lm/main.py
onnxsim_lm/onnx_utils.py
onnxsim_lm/utils.py
onnxsimlm/__init__.py
onnxsimlm/compress_model.py
onnxsimlm/main.py
onnxsimlm/onnx_utils.py
onnxsimlm/utils.py
onnxsim_lm-0.1.1.dist-info/LICENSE
onnxsim_lm-0.1.1.dist-info/METADATA
onnxsim_lm-0.1.1.dist-info/WHEEL
onnxsim_lm-0.1.1.dist-info/entry_points.txt
onnxsim_lm-0.1.1.dist-info/top_level.txt
onnxsim_lm-0.1.1.dist-info/RECORD
